pyid/__init__.py
pyid/pyid.py
pyid-0.0.3.dist-info/METADATA
pyid-0.0.3.dist-info/WHEEL
pyid-0.0.3.dist-info/top_level.txt
pyid-0.0.3.dist-info/RECORD
