Metadata-Version: 2.1
Name: pyid
Version: 0.0.3
Summary: ID attributes for python objects
Home-page: https://github.com/cyclecycle/pyid
Author: Nicholas Morley
Author-email: nick.morley111@gmail.com
License: UNKNOWN
Platform: UNKNOWN
Classifier: Programming Language :: Python :: 3
Classifier: License :: OSI Approved :: MIT License
Classifier: Operating System :: OS Independent
